worldtimeconverter/__init__.py
worldtimeconverter/converter.py
worldtimeconverter/exceptions.py
worldtimeconverter/types.py
worldtimeconverter-1.0.3.dist-info/METADATA
worldtimeconverter-1.0.3.dist-info/WHEEL
worldtimeconverter-1.0.3.dist-info/top_level.txt
worldtimeconverter-1.0.3.dist-info/RECORD
