Metadata-Version: 2.1
Name: worldtimeconverter
Version: 1.0.3
Summary: Advanced time conversion and timezone management library
Home-page: https://github.com/OrenGrinker/worldtimeconverter
Author: Oren Grinker
Author-email: orengr4@gmail.com
Project-URL: Bug Tracker, https://github.com/OrenGrinker/worldtimeconverter/issues
Keywords: timezone,time-conversion,business-hours,working-hours,holiday-calendar,python,pytz,time-management,date-time,world-clock
Classifier: Programming Language :: Python :: 3
Classifier: License :: OSI Approved :: MIT License
Classifier: Operating System :: OS Independent
Requires-Python: >=3.7
Requires-Dist: pytz>=2021.1
Requires-Dist: python-dateutil>=2.8.2
